AUTHORS.rst
CHANGES.rst
LICENSE.rst
MANIFEST.in
README.rst
TODO.rst
setup.cfg
setup.py
birdhousebuilder/__init__.py
birdhousebuilder.recipe.adagucserver.egg-info/PKG-INFO
birdhousebuilder.recipe.adagucserver.egg-info/SOURCES.txt
birdhousebuilder.recipe.adagucserver.egg-info/dependency_links.txt
birdhousebuilder.recipe.adagucserver.egg-info/entry_points.txt
birdhousebuilder.recipe.adagucserver.egg-info/namespace_packages.txt
birdhousebuilder.recipe.adagucserver.egg-info/not-zip-safe
birdhousebuilder.recipe.adagucserver.egg-info/pbr.json
birdhousebuilder.recipe.adagucserver.egg-info/requires.txt
birdhousebuilder.recipe.adagucserver.egg-info/top_level.txt
birdhousebuilder/recipe/__init__.py
birdhousebuilder/recipe/adagucserver/__init__.py
birdhousebuilder/recipe/adagucserver/adaguc.autoresource.xml
birdhousebuilder/recipe/adagucserver/adagucserver.py
birdhousebuilder/recipe/adagucserver/gunicorn.conf.py
birdhousebuilder/recipe/adagucserver/nginx.conf
birdhousebuilder/recipe/adagucserver/tests/__init__.py
birdhousebuilder/recipe/adagucserver/tests/test_docs.py