Metadata-Version: 1.1
Name: birdhousebuilder.recipe.adagucserver
Version: 0.3.4
Summary: A Buildout recipe to install and configure Adaguc Web Map Service with Anaconda.
Home-page: https://github.com/bird-house/birdhousebuilder.recipe.adagucserver
Author: Birdhouse
Author-email: UNKNOWN
License: BSD
Keywords: buildout recipe pywps wms birdhouse conda anaconda
Platform: UNKNOWN
Classifier: Framework :: Buildout
Classifier: Intended Audience :: Developers
Classifier: Topic :: Software Development :: Build Tools
Classifier: Topic :: Software Development :: Libraries :: Python Modules
Classifier: License :: OSI Approved :: BSD License
